infactory_client/__init__.py
infactory_client/base.py
infactory_client/cli.py
infactory_client/client.py
infactory_client/errors.py
infactory_client/models.py
infactory_client/services.py
infactory-0.0.3.dist-info/METADATA
infactory-0.0.3.dist-info/WHEEL
infactory-0.0.3.dist-info/entry_points.txt
infactory-0.0.3.dist-info/RECORD
