Metadata-Version: 2.3
Name: infactory
Version: 0.0.3
Summary: Infactory Python Package -  Instantly connects your data sources, generate accurate queries, and give yourself complete control over AI responses.
License: Infactory Python SDK
Keywords: ai,data,query,infactory
Author: Ken Kocienda
Author-email: kocienda@infactory.ai
Requires-Python: >=3.11,<=3.13
Classifier: Development Status :: 4 - Beta
Classifier: Intended Audience :: Developers
Classifier: License :: Other/Proprietary License
Classifier: Programming Language :: Python :: 3
Classifier: Programming Language :: Python :: 3.11
Classifier: Programming Language :: Python :: 3.12
Classifier: Programming Language :: Python :: 3.13
Classifier: Topic :: Software Development :: Libraries :: Python Modules
Requires-Dist: httpx (>=0.27.2,<0.28.0)
Requires-Dist: pydantic (>=2.9.2,<3.0.0)
Requires-Dist: python-dateutil (>=2.9.0.post0,<3.0.0)
Requires-Dist: python-dotenv (>=1.1.0,<2.0.0)
Requires-Dist: tenacity (>=9.0.0,<10.0.0)
Requires-Dist: typer (>=0.15.2,<0.16.0)
Requires-Dist: typing-extensions (>=4.12.2,<5.0.0)
Requires-Dist: urllib3 (>=2.2.3,<3.0.0)
Project-URL: Documentation, https://docs.infactory.ai
Project-URL: Homepage, https://infactory.ai
Project-URL: Repository, https://github.com/infactory-io/infactory-py
